README.rst
setup.py
fdfs_tornado/__init__.py
fdfs_tornado/client.py
fdfs_tornado/constants.py
fdfs_tornado/pool.py
fdfs_tornado/storage.py
fdfs_tornado/tracker.py
fdfs_tornado.egg-info/PKG-INFO
fdfs_tornado.egg-info/SOURCES.txt
fdfs_tornado.egg-info/dependency_links.txt
fdfs_tornado.egg-info/pbr.json
fdfs_tornado.egg-info/requires.txt
fdfs_tornado.egg-info/top_level.txt