Metadata-Version: 1.1
Name: fdfs-tornado
Version: 0.1a1
Summary: Async FDFS Client for tornado
Home-page: http://git.elenet.me/opdev/eoc-api.git
Author: WangST
Author-email: wangst321@gmail.com
License: UNKNOWN
Platform: UNKNOWN
Classifier: Development Status :: 2 - Pre-Alpha
Classifier: Intended Audience :: Developers
Classifier: Natural Language :: English
Classifier: Programming Language :: Python :: 3.4
